watchio/__init__.py
watchio-0.0.40.dist-info/LICENSE
watchio-0.0.40.dist-info/METADATA
watchio-0.0.40.dist-info/WHEEL
watchio-0.0.40.dist-info/entry_points.txt
watchio-0.0.40.dist-info/top_level.txt
watchio-0.0.40.dist-info/RECORD
