Metadata-Version: 2.1
Name: watchio
Version: 0.0.40
Summary: Process IO Watcher
Home-page: https://koobedoc.github.io/watchio/
License: GNU GPLv3
Keywords: process io
Platform: UNKNOWN
Classifier: Topic :: Utilities
Classifier: Operating System :: Unix
License-File: LICENSE
Requires-Dist: psutil
